margin_talib_service/__init__.py
margin_talib_service/__main__.py
margin_talib_service/service.py
margin_talib_service-0.0.3.dist-info/LICENSE
margin_talib_service-0.0.3.dist-info/METADATA
margin_talib_service-0.0.3.dist-info/WHEEL
margin_talib_service-0.0.3.dist-info/entry_points.txt
margin_talib_service-0.0.3.dist-info/top_level.txt
margin_talib_service-0.0.3.dist-info/RECORD
