Metadata-Version: 2.1
Name: margin-talib-service
Version: 0.0.3
Summary: Margin Strategy Editor SDK
Home-page: https://github.com/MarginOpenSource/strategy-sdk
Author: Margin UG
Author-email: contact@margin.io
License: UNKNOWN
Platform: UNKNOWN
Classifier: Programming Language :: Python :: 3
Classifier: License :: OSI Approved :: MIT License
Classifier: Operating System :: OS Independent
Requires-Python: >=3.5
License-File: LICENSE
Requires-Dist: rpyc
Requires-Dist: TA-Lib
